androidtv/__init__.py
androidtv/constants.py
androidtv/exceptions.py
androidtv/setup_async.py
androidtv/adb_manager/__init__.py
androidtv/adb_manager/adb_manager_async.py
androidtv/adb_manager/adb_manager_sync.py
androidtv/androidtv/__init__.py
androidtv/androidtv/androidtv_async.py
androidtv/androidtv/androidtv_sync.py
androidtv/androidtv/base_androidtv.py
androidtv/basetv/__init__.py
androidtv/basetv/basetv.py
androidtv/basetv/basetv_async.py
androidtv/basetv/basetv_sync.py
androidtv/firetv/__init__.py
androidtv/firetv/base_firetv.py
androidtv/firetv/firetv_async.py
androidtv/firetv/firetv_sync.py
androidtv-0.0.70.dist-info/LICENSE
androidtv-0.0.70.dist-info/METADATA
androidtv-0.0.70.dist-info/WHEEL
androidtv-0.0.70.dist-info/top_level.txt
androidtv-0.0.70.dist-info/RECORD
