Metadata-Version: 2.1
Name: androidtv
Version: 0.0.70
Summary: Communicate with an Android TV or Fire TV device via ADB over a network.
Home-page: https://github.com/JeffLIrion/python-androidtv/
Author: Jeff Irion
Author-email: jefflirion@users.noreply.github.com
License: MIT
Keywords: adb,android,androidtv,firetv
Platform: UNKNOWN
Classifier: License :: OSI Approved :: MIT License
Classifier: Operating System :: OS Independent
Classifier: Programming Language :: Python :: 3
Classifier: Programming Language :: Python :: 2
License-File: LICENSE
Requires-Dist: adb-shell (>=0.4.0)
Requires-Dist: pure-python-adb (>=0.3.0.dev0)
Provides-Extra: async
Requires-Dist: aiofiles (>=0.4.0) ; extra == 'async'
Provides-Extra: usb
Requires-Dist: adb-shell[usb] (>=0.4.0) ; extra == 'usb'
